{
    "ServerLanguage": {
        "python": {
            "json": {
                "GET": [],
                "POST": []
            },
            "calc": {
                "GET": []
            },
            "html": {
                "GET": []
            }
        },
        "javascript": {
            "json": {
                "GET": [],
                "POST": []
            },
            "calc": {
                "GET": []
            },
            "html": {
                "GET": []
            }
        }
    }
}